[
  {
    "href": "https://bit.ly/4dbUZgW",
    "text": "collect free coins 30.7.2024"
  },
  {
    "href": "https://bit.ly/3zQx4oN",
    "text": "collect free coins 30.7.2024"
  },
  {
    "href": "https://bit.ly/4f8mAkZ",
    "text": "collect free coins 29.7.2024"
  },
  {
    "href": "https://bit.ly/3A5btsE",
    "text": "collect free coins 29.7.2024"
  },
  {
    "href": "https://bit.ly/3LxrzOx",
    "text": "collect free coins 28.7.2024"
  },
  {
    "href": "https://bit.ly/3Lz9i39",
    "text": ".collect free coins 28.7.2024"
  },
  {
    "href": "https://bit.ly/3Ya7169",
    "text": "collect free coins 27.7.2024"
  },
  {
    "href": "https://bit.ly/4c0ZoCe",
    "text": "collect free coins 27.7.2024"
  },
  {
    "href": "https://bit.ly/4d8yskW",
    "text": ".collect free coins 26.7.2024"
  },
  {
    "href": "https://bit.ly/4dvSxlF",
    "text": "collect free coins 26.7.2024"
  },
  {
    "href": "https://bit.ly/3Yy4oeL",
    "text": "collect free coins 26.7.2024"
  },
  {
    "href": "https://bit.ly/4dag1wk",
    "text": "collect free coins 26.7.2024"
  },
  {
    "href": "https://bit.ly/3zPgAxl",
    "text": "collect free coins 25.7.2024"
  },
  {
    "href": "https://bit.ly/4faQULD",
    "text": "collect free coins 25.7.2024"
  },
  {
    "href": "https://bit.ly/3Svh1U3",
    "text": ".collect free coins 23.7.2024"
  },
  {
    "href": "https://bit.ly/3WlwUhP",
    "text": "collect free coins 23.7.2024"
  },
  {
    "href": "https://bit.ly/4bKhh88",
    "text": ".collect free coins 23.7.2024"
  },
  {
    "href": "https://bit.ly/3y0FqJV",
    "text": ".collect free coins 23.7.2024"
  },
  {
    "href": "https://bit.ly/4cN1uqD",
    "text": "collect free coins 22.7.2024"
  },
  {
    "href": "https://bit.ly/4bSfqyj",
    "text": "collect free coins 22.7.2024"
  },
  {
    "href": "https://bit.ly/4cRBcU2",
    "text": ".collect free coins 22.7.2024"
  },
  {
    "href": "https://bit.ly/4f9SgGv",
    "text": "collect free coins 22.7.2024"
  },
  {
    "href": "https://bit.ly/4cZRA4z",
    "text": "collect free coins 21.7.2024"
  },
  {
    "href": "https://bit.ly/3LlkFf0",
    "text": "collect free coins 21.7.2024"
  },
  {
    "href": "https://bit.ly/3W4eZev",
    "text": "collect free coins 20.7.2024"
  },
  {
    "href": "https://bit.ly/4eUFag6",
    "text": ".collect free coins 20.7.2024"
  },
  {
    "href": "https://bit.ly/466FxQO",
    "text": "collect free coins 20.7.2024"
  },
  {
    "href": "https://bit.ly/3LuGOHH",
    "text": ".collect free coins 20.7.2024"
  },
  {
    "href": "https://bit.ly/4cA4RBe",
    "text": "collect free coins 19.7.2024"
  },
  {
    "href": "https://bit.ly/3xKMOcq",
    "text": "collect free coins 19.7.2024"
  },
  {
    "href": "https://bit.ly/3xVKlvO",
    "text": "collect free coins 18.7.2024"
  },
  {
    "href": "https://bit.ly/460gJd8",
    "text": "collect free coins 18.7.2024"
  },
  {
    "href": "https://bit.ly/3zEKYKA",
    "text": "collect free coins 18.7.2024"
  },
  {
    "href": "https://bit.ly/4bEVNtm",
    "text": "collect free coins 18.7.2024"
  },
  {
    "href": "https://bit.ly/4cOJbki",
    "text": "collect free coins 17.7.2024"
  },
  {
    "href": "https://bit.ly/4bxItHk",
    "text": "collect free coins 17.7.2024"
  },
  {
    "href": "https://bit.ly/4cCfhjC",
    "text": ".collect free coins 16.7.2024"
  },
  {
    "href": "https://bit.ly/3zK8NAL",
    "text": "collect free coins 16.7.2024"
  },
  {
    "href": "https://bit.ly/3xTbUWu",
    "text": ".collect free coins 16.7.2024"
  },
  {
    "href": "https://bit.ly/45WWf4S",
    "text": "collect free coins 16.7.2024"
  },
  {
    "href": "https://bit.ly/3zxsr2W",
    "text": ".collect free coins 15.7.2024"
  },
  {
    "href": "https://bit.ly/3S428Yy",
    "text": "collect free coins 15.7.2024"
  },
  {
    "href": "https://bit.ly/3xOEx7e",
    "text": ".collect free coins 15.7.2024"
  },
  {
    "href": "https://bit.ly/4eXLuUg",
    "text": "collect free coins 15.7.2024"
  },
  {
    "href": "https://bit.ly/3RUSyH4",
    "text": "collect free coins 14.7.2024"
  },
  {
    "href": "https://bit.ly/3zFkqZu",
    "text": "collect free coins 14.7.2024"
  },
  {
    "href": "https://bit.ly/3WavXJ6",
    "text": "collect free coins 13.7.2024"
  },
  {
    "href": "https://bit.ly/4bLzJxv",
    "text": "collect free coins 13.7.2024"
  },
  {
    "href": "https://bit.ly/3Wf0Qfz",
    "text": "collect free coins 12.7.2024"
  },
  {
    "href": "https://bit.ly/3S0X1Zc",
    "text": ".collect free coins 12.7.2024"
  },
  {
    "href": "https://bit.ly/3xKI6LC",
    "text": ".collect free coins 12.7.2024"
  },
  {
    "href": "https://bit.ly/3RWfvd3",
    "text": ".collect free coins 12.7.2024"
  },
  {
    "href": "https://bit.ly/4eUlLfk",
    "text": "collect free coins 11.7.2024"
  },
  {
    "href": "https://bit.ly/4eZA2aO",
    "text": "collect free coins 11.7.2024"
  },
  {
    "href": "https://bit.ly/3S7bDpZ",
    "text": "collect free coins 11.7.2024"
  },
  {
    "href": "https://bit.ly/4eFFMGs",
    "text": "collect free coins 11.7.2024"
  },
  {
    "href": "https://bit.ly/3L9Eea6",
    "text": ".collect free coins 11.7.2024"
  },
  {
    "href": "https://bit.ly/3W3Yct9",
    "text": ".collect free coins 11.7.2024"
  },
  {
    "href": "https://bit.ly/3L5ZjCn",
    "text": "collect free coins 10.7.2024"
  },
  {
    "href": "https://bit.ly/3L7tkBD",
    "text": "collect free coins 10.7.2024"
  },
  {
    "href": "https://bit.ly/3L1Elo6",
    "text": "collect free coins 09.7.2024"
  },
  {
    "href": "https://bit.ly/4cyK3ti",
    "text": "collect free coins 09.7.2024"
  },
  {
    "href": "https://bit.ly/4cCnK5X",
    "text": "collect free coins 09.7.2024"
  },
  {
    "href": "https://bit.ly/4cBqwsh",
    "text": "collect free coins 09.7.2024"
  },
  {
    "href": "https://bit.ly/4eEeKz6",
    "text": "collect free coins 08.7.2024"
  },
  {
    "href": "https://bit.ly/3RLa6p7",
    "text": "collect free coins 08.7.2024"
  },
  {
    "href": "https://bit.ly/3xCAR8r",
    "text": "collect free coins 07.7.2024"
  },
  {
    "href": "https://bit.ly/4cyJm3a",
    "text": ".collect free coins 07.7.2024"
  },
  {
    "href": "https://bit.ly/3VI5dhK",
    "text": ".collect free coins 07.7.2024"
  },
  {
    "href": "https://bit.ly/3VNmA0W",
    "text": "collect free coins 07.7.2024"
  },
  {
    "href": "https://bit.ly/3VHjFqd",
    "text": "collect free coins 06.7.2024"
  },
  {
    "href": "https://bit.ly/3ziNnul",
    "text": ".collect free coins 06.7.2024"
  },
  {
    "href": "https://bit.ly/3KWBcWJ",
    "text": ".collect free coins 06.7.2024"
  },
  {
    "href": "https://bit.ly/3LkSPQh",
    "text": "collect free coins 06.7.2024"
  },
  {
    "href": "https://bit.ly/3LkNIQ5",
    "text": "collect free coins 05.7.2024"
  },
  {
    "href": "https://bit.ly/3KYEoRy",
    "text": "collect free coins 05.7.2024"
  },
  {
    "href": "https://bit.ly/3zrekvI",
    "text": "collect free coins 04.7.2024"
  },
  {
    "href": "https://bit.ly/4cbVuay",
    "text": "collect free coins 04.7.2024"
  },
  {
    "href": "https://bit.ly/4boPkTc",
    "text": "collect free coins 04.7.2024"
  },
  {
    "href": "https://bit.ly/4exOYN7",
    "text": ".collect free coins 04.7.2024"
  },
  {
    "href": "https://bit.ly/4bmLCtc",
    "text": "collect free coins 03.7.2024"
  },
  {
    "href": "https://bit.ly/3xykjhQ",
    "text": "collect free coins 03.7.2024"
  },
  {
    "href": "https://bit.ly/3L9E8iK",
    "text": "collect free coins 02.7.2024"
  },
  {
    "href": "https://bit.ly/3XM6siw",
    "text": ".collect free coins 02.7.2024"
  },
  {
    "href": "https://bit.ly/4cBjNP3",
    "text": ".collect free coins 01.7.2024"
  },
  {
    "href": "https://bit.ly/4eEqyRN",
    "text": ".collect free coins 01.7.2024"
  },
  {
    "href": "https://bit.ly/3xyqhze",
    "text": "collect free coins 01.7.2024"
  },
  {
    "href": "https://bit.ly/3zu13T6",
    "text": ".collect free coins 01.7.2024"
  },
  {
    "href": "https://bit.ly/4cFX3gZ",
    "text": ".collect free coins 30.6.2024"
  },
  {
    "href": "https://bit.ly/3ze4g9k",
    "text": "collect free coins 30.6.2024"
  },
  {
    "href": "https://bit.ly/3RImCpB",
    "text": "collect free coins 29.6.2024"
  },
  {
    "href": "https://bit.ly/3RF4i0A",
    "text": "collect free coins 29.6.2024"
  },
  {
    "href": "https://bit.ly/4cyDgzR",
    "text": "collect free coins 29.6.2024"
  },
  {
    "href": "https://bit.ly/4cBq0uf",
    "text": "collect free coins 29.6.2024"
  },
  {
    "href": "https://bit.ly/3KZUgDn",
    "text": "collect free coins 27.6.2024"
  },
  {
    "href": "https://bit.ly/4eE8XJS",
    "text": ".collect free coins 27.6.2024"
  },
  {
    "href": "https://bit.ly/4cw8JTq",
    "text": ".collect free coins 26.6.2024"
  },
  {
    "href": "https://bit.ly/3zkGIj6",
    "text": "collect free coins 26.6.2024"
  },
  {
    "href": "https://bit.ly/4cs8mcn",
    "text": "collect free coins 25.6.2024"
  },
  {
    "href": "https://bit.ly/3VSVbvq",
    "text": "collect free coins 25.6.2024"
  },
  {
    "href": "https://bit.ly/45HeXgT",
    "text": ".gametwist free coins 24.6.2024"
  },
  {
    "href": "https://bit.ly/4bj74PU",
    "text": "gametwist free coins 24.6.2024"
  },
  {
    "href": "https://bit.ly/4bj716G",
    "text": "gametwist free coins 23.6.2024"
  },
  {
    "href": "https://bit.ly/4bcVB4k",
    "text": "gametwist free coins 23.6.2024"
  },
  {
    "href": "https://bit.ly/3zd6Ex8",
    "text": "gametwist free coins 22.6.2024"
  },
  {
    "href": "https://bit.ly/4cs77dd",
    "text": "gametwist free coins 22.6.2024"
  },
  {
    "href": "https://bit.ly/3znoFJ2",
    "text": "gametwist free coins 21.6.2024"
  },
  {
    "href": "https://bit.ly/3VPqzv1",
    "text": ".gametwist free coins 21.6.2024"
  },
  {
    "href": "https://bit.ly/3xvG41R",
    "text": "gametwist free coins 21.6.2024"
  },
  {
    "href": "https://bit.ly/3XtcQLD",
    "text": "gametwist free coins 21.6.2024"
  },
  {
    "href": "https://bit.ly/3KMg5WV",
    "text": "gametwist free coins 20.6.2024"
  },
  {
    "href": "https://bit.ly/3VpYWY8",
    "text": ".gametwist free coins 20.6.2024"
  },
  {
    "href": "https://bit.ly/4cozgSl",
    "text": "gametwist free coins 20.6.2024"
  },
  {
    "href": "https://bit.ly/4c3fvzU",
    "text": ".gametwist free coins 20.6.2024"
  },
  {
    "href": "https://bit.ly/4epUMrE",
    "text": "gametwist free coins 19.6.2024"
  },
  {
    "href": "https://bit.ly/3Vu84uv",
    "text": "gametwist free coins 19.6.2024"
  },
  {
    "href": "https://bit.ly/3XNpbur",
    "text": "gametwist free coins 19.6.2024"
  },
  {
    "href": "https://bit.ly/45uzxkm",
    "text": "gametwist free coins 19.6.2024"
  },
  {
    "href": "https://bit.ly/4ciIWyp",
    "text": "gametwist free coins 19.6.2024"
  },
  {
    "href": "https://bit.ly/3VJOuMc",
    "text": "gametwist free coins 19.6.2024"
  },
  {
    "href": "https://bit.ly/4c0tBSP",
    "text": "gametwist free coins 18.6.2024"
  },
  {
    "href": "https://bit.ly/45ra8bo",
    "text": "gametwist free coins 18.6.2024"
  },
  {
    "href": "https://bit.ly/3XpFihi",
    "text": "gametwist free coins 18.6.2024"
  },
  {
    "href": "https://bit.ly/4eop0eK",
    "text": "gametwist free coins 18.6.2024"
  },
  {
    "href": "https://bit.ly/3Vxg27A",
    "text": "gametwist free coins 17.6.2024"
  },
  {
    "href": "https://bit.ly/3VB3HPR",
    "text": "gametwist free coins 17.6.2024"
  },
  {
    "href": "https://bit.ly/4ejt283",
    "text": "gametwist free coins 17.6.2024"
  },
  {
    "href": "https://bit.ly/3VxZRa8",
    "text": "gametwist free coins 17.6.2024"
  },
  {
    "href": "https://bit.ly/4eeYi8k",
    "text": "gametwist free coins 16.6.2024"
  },
  {
    "href": "https://bit.ly/4ehPte4",
    "text": "gametwist free coins 16.6.2024"
  },
  {
    "href": "https://bit.ly/3KCDQkb",
    "text": "gametwist free coins 16.6.2024"
  },
  {
    "href": "https://bit.ly/3Xh1w53",
    "text": "gametwist free coins 16.6.2024"
  },
  {
    "href": "https://bit.ly/4c949do",
    "text": "gametwist free coins 15.6.2024"
  },
  {
    "href": "https://bit.ly/4eh9ktF",
    "text": ".gametwist free coins 15.6.2024"
  },
  {
    "href": "https://bit.ly/3VBvsrA",
    "text": "gametwist free coins 15.6.2024"
  },
  {
    "href": "https://bit.ly/4bSFV7o",
    "text": "gametwist free coins 15.6.2024"
  },
  {
    "href": "https://bit.ly/3yI4IN6",
    "text": ".gametwist free coins 14.6.2024"
  },
  {
    "href": "https://bit.ly/44YIOkB",
    "text": ".gametwist free coins 14.6.2024"
  },
  {
    "href": "https://bit.ly/3Kil9lA",
    "text": "gametwist free coins 14.6.2024"
  },
  {
    "href": "https://bit.ly/3KhCXNT",
    "text": "gametwist free coins 14.6.2024"
  },
  {
    "href": "https://bit.ly/3XgFuzr",
    "text": ".gametwist free coins 13.6.2024"
  },
  {
    "href": "https://bit.ly/3XewydS",
    "text": "gametwist free coins 13.6.2024"
  },
  {
    "href": "https://bit.ly/3Kk372f",
    "text": "gametwist free coins 13.6.2024"
  },
  {
    "href": "https://bit.ly/3KFXjRb",
    "text": "gametwist free coins 13.6.2024"
  },
  {
    "href": "https://bit.ly/3WZCbfK",
    "text": "gametwist free coins 13.6.2024"
  },
  {
    "href": "https://bit.ly/3WZreea",
    "text": ".gametwist free coins 13.6.2024"
  },
  {
    "href": "https://bit.ly/3KmEvGi",
    "text": "gametwist free coins 12.6.2024"
  },
  {
    "href": "https://bit.ly/3Km5lhN",
    "text": ".gametwist free coins 12.6.2024"
  },
  {
    "href": "https://bit.ly/3R5clmK",
    "text": "gametwist free coins 11.6.2024"
  },
  {
    "href": "https://bit.ly/3R5cuqi",
    "text": "gametwist free coins 11.6.2024"
  },
  {
    "href": "https://bit.ly/3wTMrvu",
    "text": "gametwist free coins 10.6.2024"
  },
  {
    "href": "https://bit.ly/3R34TbU",
    "text": "gametwist free coins 10.6.2024"
  },
  {
    "href": "https://bit.ly/4e2a0Ty",
    "text": "gametwist free coins 10.6.2024"
  },
  {
    "href": "https://bit.ly/3V2xIGx",
    "text": "gametwist free coins 10.6.2024"
  },
  {
    "href": "https://bit.ly/44Y035o",
    "text": "gametwist free coins 09.6.2024"
  },
  {
    "href": "https://bit.ly/3V72ezo",
    "text": ".gametwist free coins 09.6.2024"
  },
  {
    "href": "https://bit.ly/4bGEg56",
    "text": "gametwist free coins 08.6.2024"
  },
  {
    "href": "https://bit.ly/3VihXwJ",
    "text": ".gametwist free coins 08.6.2024"
  },
  {
    "href": "https://bit.ly/44XeLKb",
    "text": ".gametwist free coins 08.6.2024"
  },
  {
    "href": "https://bit.ly/3x0rY8f",
    "text": "gametwist free coins 08.6.2024"
  },
  {
    "href": "https://bit.ly/4bA8XbY",
    "text": "gametwist free coins 07.6.2024"
  },
  {
    "href": "https://bit.ly/3V11ziB",
    "text": "gametwist free coins 07.6.2024"
  },
  {
    "href": "https://bit.ly/3wWcja7",
    "text": ".gametwist free coins 06.6.2024"
  },
  {
    "href": "https://bit.ly/3WY8CLy",
    "text": ".gametwist free coins 06.6.2024"
  },
  {
    "href": "https://bit.ly/3X4rskx",
    "text": ".gametwist free coins 06.6.2024"
  },
  {
    "href": "https://bit.ly/3wW89Px",
    "text": ".gametwist free coins 06.6.2024"
  },
  {
    "href": "https://bit.ly/3wJORNo",
    "text": ".gametwist free coins 05.6.2024"
  },
  {
    "href": "https://bit.ly/3X4rk4x",
    "text": "gametwist free coins 05.6.2024"
  },
  {
    "href": "https://bit.ly/3X4r4m5",
    "text": ".gametwist free coins 04.6.2024"
  },
  {
    "href": "https://bit.ly/4bW4Kze",
    "text": "gametwist free coins 04.6.2024"
  },
  {
    "href": "https://bit.ly/3X4r4m5",
    "text": "gametwist free coins 04.6.2024"
  },
  {
    "href": "https://bit.ly/4bW4Kze",
    "text": ".gametwist free coins 04.6.2024"
  },
  {
    "href": "https://bit.ly/3Kljmwk",
    "text": "gametwist free coins 03.6.2024"
  },
  {
    "href": "https://bit.ly/3R56Btn",
    "text": "gametwist free coins 03.6.2024"
  },
  {
    "href": "https://bit.ly/3KgG4p8",
    "text": "gametwist free coins 02.6.2024"
  },
  {
    "href": "https://bit.ly/3x3Fzvw",
    "text": "gametwist free coins 02.6.2024"
  },
  {
    "href": "https://bit.ly/3Kjv8XT",
    "text": "gametwist free coins 01.6.2024"
  },
  {
    "href": "https://bit.ly/3yCGDHo",
    "text": "gametwist free coins 01.6.2024"
  },
  {
    "href": "https://bit.ly/3UXLoTs",
    "text": "gametwist free coins 01.6.2024"
  },
  {
    "href": "https://bit.ly/4dZxusI",
    "text": ".gametwist free coins 01.6.2024"
  },
  {
    "href": "https://bit.ly/4bRGv55",
    "text": "gametwist free coins 31.5.2024"
  },
  {
    "href": "https://bit.ly/3UWVvba",
    "text": ".gametwist free coins 31.5.2024"
  },
  {
    "href": "https://bit.ly/453pRgP",
    "text": "gametwist free coins 30.5.2024"
  },
  {
    "href": "https://bit.ly/4bUeSIC",
    "text": "gametwist free coins 30.5.2024"
  },
  {
    "href": "https://bit.ly/4bTOK0C",
    "text": "gametwist free coins 30.5.2024"
  },
  {
    "href": "https://bit.ly/3yzKZPB",
    "text": ".gametwist free coins 30.5.2024"
  },
  {
    "href": "https://bit.ly/3yvkhHC",
    "text": "gametwistfree coins 29.5.2024"
  },
  {
    "href": "https://bit.ly/44Y7TfA",
    "text": ".gametwistfree coins 29.5.2024"
  },
  {
    "href": "https://bit.ly/44WALEZ",
    "text": ".gametwistfree coins 29.5.2024"
  },
  {
    "href": "https://bit.ly/3yEplcY",
    "text": "gametwistfree coins 29.5.2024"
  },
  {
    "href": "https://bit.ly/4bGq4Jm",
    "text": "gametwist free coins 28.5.2024"
  },
  {
    "href": "https://bit.ly/4bzQVXd",
    "text": ".gametwist free coins 28.5.2024"
  },
  {
    "href": "https://bit.ly/44uGsJS",
    "text": "gametwist free coins 27.5.2024"
  },
  {
    "href": "https://bit.ly/4aij57W",
    "text": ".gametwist free coins 27.5.2024"
  },
  {
    "href": "https://bit.ly/3Q1pih1",
    "text": ".gametwist free coins 27.5.2024"
  },
  {
    "href": "https://bit.ly/3PSCNje",
    "text": ".gametwist free coins 27.5.2024"
  },
  {
    "href": "https://bit.ly/3WScMVm",
    "text": ".gametwist free coins 26.5.2024"
  },
  {
    "href": "https://bit.ly/3wNKil0",
    "text": "gametwist free coins 26.5.2024"
  },
  {
    "href": "https://bit.ly/3y8zLBr",
    "text": "gametwist free coins 26.5.2024"
  },
  {
    "href": "https://bit.ly/3JRTasG",
    "text": "gametwist free coins 26.5.2024"
  },
  {
    "href": "https://bit.ly/3WwuvBv",
    "text": ".gametwist free coins 25.5.2024"
  },
  {
    "href": "https://bit.ly/44uGotC",
    "text": "gametwist free coins 25.5.2024"
  },
  {
    "href": "https://bit.ly/3woKbfw",
    "text": "gametwist free coins 25.5.2024"
  },
  {
    "href": "https://bit.ly/3Wv9XJy",
    "text": "gametwist free coins 25.5.2024"
  },
  {
    "href": "https://bit.ly/4axZWPk",
    "text": ".gametwist free coins 24.5.2024"
  },
  {
    "href": "https://bit.ly/3wZqtam",
    "text": "gametwist free coins 24.5.2024"
  },
  {
    "href": "https://bit.ly/4bsmjXb",
    "text": "gametwist free coins 24.5.2024"
  },
  {
    "href": "https://bit.ly/3UQw62T",
    "text": "gametwist free coins 24.5.2024"
  },
  {
    "href": "https://bit.ly/3y8FUxn",
    "text": ".gametwist free coins 23.5.2024"
  },
  {
    "href": "https://bit.ly/44wTh6A",
    "text": "gametwist free coins 23.5.2024"
  },
  {
    "href": "https://bit.ly/3JRoZ51",
    "text": "gametwist free coins 22.5.2024"
  },
  {
    "href": "https://bit.ly/4absGwY",
    "text": "gametwist free coins 22.5.2024"
  },
  {
    "href": "https://bit.ly/3JQAaLd",
    "text": ".gametwist free coins 22.5.2024"
  },
  {
    "href": "https://bit.ly/3WrCPmd",
    "text": "gametwist free coins 22.5.2024"
  },
  {
    "href": "https://bit.ly/4acswpl",
    "text": ".gametwist free coins 21.5.2024"
  },
  {
    "href": "https://bit.ly/4dIs1q7",
    "text": "gametwist free coins 21.5.2024"
  },
  {
    "href": "https://bit.ly/4buMGMn",
    "text": "gametwist free coins 21.5.2024"
  },
  {
    "href": "https://bit.ly/3weYeV7",
    "text": "gametwist free coins 21.5.2024"
  },
  {
    "href": "https://bit.ly/3UNLEW1",
    "text": "gametwist free coins 20.5.2024"
  },
  {
    "href": "https://bit.ly/3UP6t3z",
    "text": "gametwist free coins 20.5.2024"
  },
  {
    "href": "https://bit.ly/3QqWRJI",
    "text": ".gametwist free coins 19.5.2024"
  },
  {
    "href": "https://bit.ly/3Qo3iNA",
    "text": "gametwist free coins 19.5.2024"
  },
  {
    "href": "https://bit.ly/4acpnpr",
    "text": ".gametwist free coins 19.5.2024"
  },
  {
    "href": "https://bit.ly/3QvotNW",
    "text": ".gametwist free coins 19.5.2024"
  },
  {
    "href": "https://bit.ly/4dtCqpc",
    "text": "gametwist free coins 18.5.2024"
  },
  {
    "href": "https://bit.ly/4a9i6qj",
    "text": "gametwist free coins 18.5.2024"
  },
  {
    "href": "https://bit.ly/3JEnPcY",
    "text": "gametwist free coins 18.5.2024"
  },
  {
    "href": "https://bit.ly/3wh64NL",
    "text": ".gametwist free coins 18.5.2024"
  },
  {
    "href": "https://bit.ly/4do1qhP",
    "text": "gametwist free coins 17.5.2024"
  },
  {
    "href": "https://bit.ly/3Qz8JsZ",
    "text": "gametwist free coins 17.5.2024"
  },
  {
    "href": "https://bit.ly/3wffqcO",
    "text": "gametwist free coins 16.5.2024"
  },
  {
    "href": "https://bit.ly/3UnDK4g",
    "text": "gametwist free coins 16.5.2024"
  },
  {
    "href": "https://bit.ly/3UftVFA",
    "text": "gametwist free coins 16.5.2024"
  },
  {
    "href": "https://bit.ly/3wmOpUP",
    "text": "gametwist free coins 16.5.2024"
  },
  {
    "href": "https://bit.ly/4bhB7b7",
    "text": "gametwist free coins 15.5.2024"
  },
  {
    "href": "https://bit.ly/3wmPNH1",
    "text": "gametwist free coins 15.5.2024"
  },
  {
    "href": "https://bit.ly/3UjMgBm",
    "text": ".gametwist free coins 15.5.2024"
  },
  {
    "href": "https://bit.ly/3UokuUi",
    "text": "gametwist free coins 15.5.2024"
  },
  {
    "href": "https://bit.ly/3UlqHAn",
    "text": "gametwist free coins 14.5.2024"
  },
  {
    "href": "https://bit.ly/3y69xPE",
    "text": ".gametwist free coins 14.5.2024"
  },
  {
    "href": "https://bit.ly/3UkepIG",
    "text": "gametwist free coins 14.5.2024"
  },
  {
    "href": "https://bit.ly/3UELssk",
    "text": "gametwist free coins 14.5.2024"
  },
  {
    "href": "https://bit.ly/3U6ZSQc",
    "text": ".gametwist free coins 13.5.2024"
  },
  {
    "href": "https://bit.ly/4ddka3d",
    "text": ".gametwist free coins 13.5.2024"
  },
  {
    "href": "https://bit.ly/3xUJLOp",
    "text": "gametwist free coins 13.5.2024"
  },
  {
    "href": "https://bit.ly/3wbd273",
    "text": ".gametwist free coins 13.5.2024"
  },
  {
    "href": "https://bit.ly/3xUKyPp",
    "text": ".gametwist free coins 12.5.2024"
  },
  {
    "href": "https://bit.ly/3xUKL59",
    "text": "gametwist free coins 12.5.2024"
  },
  {
    "href": "https://bit.ly/4d9sVeJ",
    "text": ".gametwist free coins 11.5.2024"
  },
  {
    "href": "https://bit.ly/3WfLOXs",
    "text": ".gametwist free coins 11.5.2024"
  },
  {
    "href": "https://bit.ly/4dc1uRC",
    "text": "gametwist free coins 11.5.2024"
  },
  {
    "href": "https://bit.ly/4aNnXTy",
    "text": "gametwist free coins 11.5.2024"
  },
  {
    "href": "https://bit.ly/4beLX2a",
    "text": "gametwist free coins 10.5.2024"
  },
  {
    "href": "https://bit.ly/3UDPhMS",
    "text": "gametwist free coins 10.5.2024"
  },
  {
    "href": "https://bit.ly/4aM47b6",
    "text": ".gametwist free coins 10.5.2024"
  },
  {
    "href": "https://bit.ly/4dcSKdW",
    "text": "gametwist free coins 10.5.2024"
  },
  {
    "href": "https://bit.ly/3UdAIzE",
    "text": "gametwist free coins 09.5.2024"
  },
  {
    "href": "https://bit.ly/4dede63",
    "text": "gametwist free coins 09.5.2024"
  },
  {
    "href": "https://bit.ly/3Uw3mMy",
    "text": "gametwist free coins 08.5.2024"
  },
  {
    "href": "https://bit.ly/4beH896",
    "text": "gametwist free coins 08.5.2024"
  },
  {
    "href": "https://bit.ly/4dgNZQL",
    "text": "gametwist free coins 08.5.2024"
  },
  {
    "href": "https://bit.ly/4daAv93",
    "text": "gametwist free coins 08.5.2024"
  },
  {
    "href": "https://bit.ly/3JQvMvS",
    "text": "gametwist free coins 07.5.2024"
  },
  {
    "href": "https://bit.ly/3UKRwzn",
    "text": "gametwist free coins 07.5.2024"
  },
  {
    "href": "https://bit.ly/3WiDRRh",
    "text": "gametwist free coins 07.5.2024"
  },
  {
    "href": "https://bit.ly/4b2bZoU",
    "text": "gametwist free coins 07.5.2024"
  },
  {
    "href": "https://bit.ly/4aGa5dD",
    "text": ".gametwist free coins 06.5.2024"
  },
  {
    "href": "https://bit.ly/49RIjJS",
    "text": "gametwist free coins 06.5.2024"
  },
  {
    "href": "https://bit.ly/4ba5zDV",
    "text": "gametwist free coins 06.5.2024"
  },
  {
    "href": "https://bit.ly/4baUbI1",
    "text": ".gametwist free coins 06.5.2024"
  },
  {
    "href": "https://bit.ly/3UxOIpe",
    "text": "4.gametwist free coins 05.5.2024"
  },
  {
    "href": "https://bit.ly/3WgcozQ",
    "text": "gametwist free coins 05.5.2024"
  },
  {
    "href": "https://bit.ly/49RCeNs",
    "text": "gametwist free coins 05.5.2024"
  },
  {
    "href": "https://bit.ly/4dbgiA0",
    "text": "gametwist free coins 05.5.2024"
  },
  {
    "href": "https://bit.ly/3WgPubD",
    "text": ".gametwist free coins 04.5.2024"
  },
  {
    "href": "https://bit.ly/3xNSGBf",
    "text": "gametwist free coins 04.5.2024"
  },
  {
    "href": "https://bit.ly/49OTIKk",
    "text": "gametwist free coins 04.5.2024"
  },
  {
    "href": "https://bit.ly/4aKC1wN",
    "text": ".gametwist free coins 04.5.2024"
  },
  {
    "href": "https://bit.ly/3xLWxia",
    "text": "gametwist free coins 03.5.2024"
  },
  {
    "href": "https://bit.ly/49Rv8IZ",
    "text": ".gametwist free coins 03.5.2024"
  },
  {
    "href": "https://bit.ly/3UtATrH",
    "text": "gametwist free coins 02.5.2024"
  },
  {
    "href": "https://bit.ly/4dnCWFx",
    "text": "gametwist free coins 02.5.2024"
  },
  {
    "href": "https://bit.ly/3W3r9py",
    "text": "gametwist free coins 01.5.2024"
  },
  {
    "href": "https://bit.ly/3Q7v7JO",
    "text": "gametwist free coins 01.5.2024"
  }
]